bh_util/flagfolder.py
bh_util/killpill.py
bh_util/timer.py
bh_util/singletons/__init__.py
bh_util/singletons/debug.py
bh_util-1.0.0b0.dist-info/METADATA
bh_util-1.0.0b0.dist-info/WHEEL
bh_util-1.0.0b0.dist-info/top_level.txt
bh_util-1.0.0b0.dist-info/RECORD
