Metadata-Version: 2.1
Name: bh-util
Version: 1.0.0b0
Summary: Add your description here
Requires-Python: >=3.12
Requires-Dist: bh-bump>=0.1.3rc1
Requires-Dist: pytest>=8.3.4
